zpylib/__init__.py
zpylib/ast/__init__.py
zpylib/ast/lexer.py
zpylib/build/__init__.py
zpylib/build/build.py
zpylib/build/execute.py
zpylib/build/run.py
zpylib/build/save.py
zpylib/cli/__init__.py
zpylib/cli/cli.py
zpylib/compiler/__init__.py
zpylib/compiler/compiler.py
zpylib/compiler/libcollect.py
zpylib/compiler/tokenhandler.py
zpylib/grammar/__init__.py
zpylib/grammar/builtin.py
zpylib/grammar/keyword.py
zpylib/grammar/token.py
zpylib/grammar/type.py
zpylib/lib/__init__.py
zpylib/lib/lib.py
zpylib/lib/__builtin__/__init__.py
zpylib/lib/__builtin__/constants.json
zpylib/lib/__builtin__/exceptions.json
zpylib/lib/__builtin__/functions.json
zpylib/lib/__builtin__/reserved.json
zpylib/lib/__builtin__/stdtypes.json
zpylib/lib/requests/__init__.py
zpylib/lib/requests/requests.json
zpylib/lib/standard/__future__.json
zpylib/lib/standard/__init__.py
zpylib/lib/standard/__main__.json
zpylib/lib/standard/aifc.json
zpylib/lib/standard/argparse.json
zpylib/lib/standard/ast.json
zpylib/lib/standard/asynchat.json
zpylib/lib/standard/asyncio.json
zpylib/lib/standard/asyncore.json
zpylib/lib/standard/atexit.json
zpylib/lib/standard/audioop.json
zpylib/lib/standard/base64.json
zpylib/lib/standard/binascii.json
zpylib/lib/standard/binhex.json
zpylib/lib/standard/bisect.json
zpylib/lib/standard/bz2.json
zpylib/lib/standard/cgi.json
zpylib/lib/standard/chunk.json
zpylib/lib/standard/cmath.json
zpylib/lib/standard/cmd.json
zpylib/lib/standard/code.json
zpylib/lib/standard/codecs.json
zpylib/lib/standard/collections.abc.json
zpylib/lib/standard/collections.json
zpylib/lib/standard/colorsys.json
zpylib/lib/standard/compileall.json
zpylib/lib/standard/concurrent.futures.json
zpylib/lib/standard/configparser.json
zpylib/lib/standard/contextlib.json
zpylib/lib/standard/contextvars.json
zpylib/lib/standard/copyreg.json
zpylib/lib/standard/crypt.json
zpylib/lib/standard/csv.json
zpylib/lib/standard/ctypes.json
zpylib/lib/standard/curses.json
zpylib/lib/standard/curses.panel.json
zpylib-0.2.5.dist-info/LICENSE
zpylib-0.2.5.dist-info/METADATA
zpylib-0.2.5.dist-info/WHEEL
zpylib-0.2.5.dist-info/entry_points.txt
zpylib-0.2.5.dist-info/top_level.txt
zpylib-0.2.5.dist-info/RECORD
