Metadata-Version: 2.1
Name: zpylib
Version: 0.2.5
Summary: Zpy Lib - Chinese programming lib
Home-page: https://github.com/louisyoungx/zpy-lib
Author: louisyoungx
Author-email: 1462648167@qq.com
License: UNKNOWN
Project-URL: Bug Tracker, https://github.com/louisyoungx/zpy-lib/issues
Platform: UNKNOWN
Classifier: Programming Language :: Python :: 3
Classifier: License :: OSI Approved :: MIT License
Classifier: Operating System :: OS Independent
Requires-Python: >=3.6
License-File: LICENSE
